investimentos/__init__.py
investimentos/investimentos.py
ivanissa_meu_investimento-0.2.dist-info/LICENSE
ivanissa_meu_investimento-0.2.dist-info/METADATA
ivanissa_meu_investimento-0.2.dist-info/WHEEL
ivanissa_meu_investimento-0.2.dist-info/top_level.txt
ivanissa_meu_investimento-0.2.dist-info/RECORD
