Metadata-Version: 2.1
Name: ivanissa-meu-investimento
Version: 0.2
Summary: Uma biblioteca para cálculos de investimentos.
Home-page: https://github.com/ivanissa/meu_investimento
Author: Ivan Alfredo Issa
Author-email: ivanissa.dev@gmail.com
License: MIT
Platform: UNKNOWN
Classifier: Programming Language :: Python :: 3
Classifier: License :: OSI Approved :: MIT License
Classifier: Operating System :: OS Independent
Requires-Python: >=3.6
